junyu/__init__.py
junyu/jy.py
junyu/cnn/__init__.py
junyu/cnn/efficientNet.py
junyu/cnn/resNet.py
junyu/cnn/utils.py
junyu/shenlian/Image_Pre_Treat.py
junyu/shenlian/Mvi.py
junyu/shenlian/__init__.py
junyu/shenlian/account.py
junyu/shenlian/cluster.py
junyu/shenlian/def_read.py
junyu/shenlian/files_find.py
junyu/shenlian/mudeConstant.py
junyu/shenlian/mvi_read.py
junyu/shenlian/schedule_read.py
junyu-1.0.11.dist-info/LICENSE
junyu-1.0.11.dist-info/METADATA
junyu-1.0.11.dist-info/WHEEL
junyu-1.0.11.dist-info/top_level.txt
junyu-1.0.11.dist-info/RECORD
