Metadata-Version: 2.1
Name: junyu
Version: 1.0.11
Summary: 君禹科技
Author: Li Weijian
Author-email: liweijian@junyu.ai
Classifier: Programming Language :: Python :: 3
Classifier: License :: OSI Approved :: MIT License
Classifier: Operating System :: OS Independent
Requires-Python: >=3
License-File: LICENSE
Requires-Dist: numpy (>=1.23)
Requires-Dist: Pillow (>=9.2)
